OrangeVolcanoes/GeneralThermoWidget.py
OrangeVolcanoes/OWCoDATransformations.py
OrangeVolcanoes/OWDataCleaning.py
OrangeVolcanoes/OWDatasets.py
OrangeVolcanoes/__init__.py
OrangeVolcanoes/datasets/Georoc_Cpx_Selected.xlsx
OrangeVolcanoes/datasets/Pawlowsky-Glahn_and_Egozcue_2006.xlsx
OrangeVolcanoes/datasets/Petrelli_et_al_2020__Test_Dataset.xlsx
OrangeVolcanoes/datasets/Petrelli_et_al_2020__Train_Dataset.xlsx
OrangeVolcanoes/datasets/Smith_et_al_2011.xlsx
OrangeVolcanoes/icons/.DS_Store
OrangeVolcanoes/icons/CoDATransformations.png
OrangeVolcanoes/icons/CpxBaromether.png
OrangeVolcanoes/icons/CpxOpx_icon.png
OrangeVolcanoes/icons/CpxThermometer.png
OrangeVolcanoes/icons/Cpx_Barometer_icon.png
OrangeVolcanoes/icons/Cpx_Opx_Thermometer.png
OrangeVolcanoes/icons/DataCleaning.png
OrangeVolcanoes/icons/Datasets.png
OrangeVolcanoes/icons/LiqThermometer.png
OrangeVolcanoes/icons/Opx_Barometer_icon.png
OrangeVolcanoes/icons/Opx_Thermometer_icon.png
OrangeVolcanoes/icons/PT_Preprocessing.png
OrangeVolcanoes/icons/TEST.png
OrangeVolcanoes/icons/Thermobarometer.png
OrangeVolcanoes/icons/Viscosity.afdesign
OrangeVolcanoes/icons/Viscosity.png
OrangeVolcanoes/icons/Volcano.png
OrangeVolcanoes/icons/thermobar.png
OrangeVolcanoes/utils/__init__.py
OrangeVolcanoes/utils/dataManipulation.py
orange3_volcanoes-1.0.41.dist-info/licenses/LICENCE
orange3_volcanoes-1.0.41.dist-info/METADATA
orange3_volcanoes-1.0.41.dist-info/WHEEL
orange3_volcanoes-1.0.41.dist-info/entry_points.txt
orange3_volcanoes-1.0.41.dist-info/top_level.txt
orange3_volcanoes-1.0.41.dist-info/RECORD
