Metadata-Version: 2.4
Name: orange3-volcanoes
Version: 1.0.41
Summary: Orange-Volcanoes is an extension (add-on) of the open-source Orange data mining platform, specifically designed to support data-driven investigations in petrology and volcanology.
Author-email: Murizio Petrelli <muripetre@gmail.com>
Project-URL: Source, https://github.com/AIVolcanoLab/orange3-volcanoes
Requires-Python: >=3.8
License-File: LICENCE
Requires-Dist: requests>=2.0
Requires-Dist: Thermobar
Dynamic: license-file
